attrs_jsonschema/__init__.py
attrs_jsonschema/compat.py
attrs_jsonschema/exceptions.py
attrs_jsonschema/tests/__init__.py
attrs_jsonschema/tests/test_full.py
attrs_jsonschema-0.2.dist-info/DESCRIPTION.rst
attrs_jsonschema-0.2.dist-info/METADATA
attrs_jsonschema-0.2.dist-info/RECORD
attrs_jsonschema-0.2.dist-info/WHEEL
attrs_jsonschema-0.2.dist-info/metadata.json
attrs_jsonschema-0.2.dist-info/top_level.txt
